makeplotplayable/__init__.py
makeplotplayable/_audioProcess.py
makeplotplayable/_plotProcess.py
makeplotplayable/_session.py
makeplotplayable/_util.py
playplot/__init__.py
playplot/_audioProcess.py
playplot/_plotProcess.py
playplot/_util.py
playplot/session.py
playplot-0.1.1b1.dist-info/LICENCE
playplot-0.1.1b1.dist-info/METADATA
playplot-0.1.1b1.dist-info/WHEEL
playplot-0.1.1b1.dist-info/top_level.txt
playplot-0.1.1b1.dist-info/RECORD
