Metadata-Version: 2.1
Name: playplot
Version: 0.1.1b1
Summary: Create and sync multiple interactive matplotlib plots to a piece of audio.
Home-page: https://github.com/groupmm/playplot
Author: Daniel Keitel
Author-email: daniel.mg.keitel@fau.de
Project-URL: Documentation, https://groupmm.github.io/playplot
Project-URL: Tracker, https://github.com/groupmm/playplot/issues
Project-URL: Source, https://github.com/groupmm/playplot/
Keywords: music,audio,matplotlib,audiolabs,visualisation
Classifier: Programming Language :: Python :: 3
Classifier: License :: OSI Approved :: MIT License
Classifier: Operating System :: OS Independent
Classifier: Intended Audience :: Developers
Classifier: Intended Audience :: Education
Classifier: Intended Audience :: Science/Research
Classifier: Topic :: Multimedia :: Graphics :: Presentation
Classifier: Topic :: Multimedia :: Sound/Audio
Classifier: Topic :: Multimedia :: Sound/Audio :: Players
Classifier: Topic :: Scientific/Engineering :: Visualization
Requires-Python: >=3.7
License-File: LICENCE
Requires-Dist: matplotlib (~=3.5.2)
Requires-Dist: miniaudio
Requires-Dist: numpy
Requires-Dist: dill
Requires-Dist: PyQt5
Requires-Dist: pycairo
Requires-Dist: SoundFile
